brom_drake/__init__.py
brom_drake/all.py
brom_drake/directories.py
brom_drake/control/__init__.py
brom_drake/control/all.py
brom_drake/control/ideal_joint_position_controller.py
brom_drake/control/arms/__init__.py
brom_drake/control/arms/arm_control_mode.py
brom_drake/control/arms/base_arm_controller.py
brom_drake/control/arms/cartesian_arm_controller.py
brom_drake/control/arms/end_effector_target.py
brom_drake/control/arms/joint_arm_controller.py
brom_drake/control/arms/joint_target.py
brom_drake/control/grippers/__init__.py
brom_drake/control/grippers/gripper_controller.py
brom_drake/control/grippers/gripper_target.py
brom_drake/example_helpers/__init__.py
brom_drake/example_helpers/block_handler_system.py
brom_drake/file_manipulation/__init__.py
brom_drake/file_manipulation/all.py
brom_drake/file_manipulation/urdf/__init__.py
brom_drake/file_manipulation/urdf/all.py
brom_drake/file_manipulation/urdf/drakeify.py
brom_drake/file_manipulation/urdf/drake_ready_urdf_converter/__init__.py
brom_drake/file_manipulation/urdf/drake_ready_urdf_converter/all.py
brom_drake/file_manipulation/urdf/drake_ready_urdf_converter/config.py
brom_drake/file_manipulation/urdf/drake_ready_urdf_converter/converter.py
brom_drake/file_manipulation/urdf/drake_ready_urdf_converter/file_manager.py
brom_drake/file_manipulation/urdf/drake_ready_urdf_converter/mesh_file_converter.py
brom_drake/file_manipulation/urdf/drake_ready_urdf_converter/util.py
brom_drake/file_manipulation/urdf/shapes/__init__.py
brom_drake/file_manipulation/urdf/shapes/all.py
brom_drake/file_manipulation/urdf/shapes/box.py
brom_drake/file_manipulation/urdf/shapes/cylinder.py
brom_drake/file_manipulation/urdf/shapes/shape_definition.py
brom_drake/file_manipulation/urdf/shapes/sphere.py
brom_drake/file_manipulation/urdf/simple_writer/__init__.py
brom_drake/file_manipulation/urdf/simple_writer/inertia_definition.py
brom_drake/file_manipulation/urdf/simple_writer/urdf_definition.py
brom_drake-0.5.0.dist-info/licenses/LICENSE
brom_drake-0.5.0.dist-info/METADATA
brom_drake-0.5.0.dist-info/WHEEL
brom_drake-0.5.0.dist-info/top_level.txt
brom_drake-0.5.0.dist-info/RECORD
