Metadata-Version: 2.4
Name: brom_drake
Version: 0.5.0
Summary: A set of convenient logging and testing tools for the Drake robotics toolbox.
Home-page: https://github.com/kwesiRutledge/brom_drake-py
Author: Kwesi Rutledge
Author-email: thesolitaryecrivain@gmail.com
Keywords: drake,robotics,testing,logging
Classifier: Programming Language :: Python :: 3
License-File: LICENSE
Requires-Dist: drake
Requires-Dist: meshcat
Requires-Dist: matplotlib
Requires-Dist: numpy
Requires-Dist: pycollada
Requires-Dist: trimesh
Requires-Dist: coacd
Dynamic: author
Dynamic: author-email
Dynamic: classifier
Dynamic: description
Dynamic: description-content-type
Dynamic: home-page
Dynamic: keywords
Dynamic: license-file
Dynamic: requires-dist
Dynamic: summary
